agent_lens_core/README.md
agent_lens_core/__init__.py
agent_lens_core/logging_config.py
agent_lens_core/utils.py
agent_lens_core/agent/prompts.py
agent_lens_core/agent/service.py
agent_lens_core/agent/tests.py
agent_lens_core/agent/views.py
agent_lens_core/agent/message_manager/service.py
agent_lens_core/agent/message_manager/tests.py
agent_lens_core/agent/message_manager/views.py
agent_lens_core/browser/browser.py
agent_lens_core/browser/context.py
agent_lens_core/browser/views.py
agent_lens_core/browser/tests/screenshot_test.py
agent_lens_core/browser/tests/test_clicks.py
agent_lens_core/controller/service.py
agent_lens_core/controller/views.py
agent_lens_core/controller/registry/service.py
agent_lens_core/controller/registry/views.py
agent_lens_core/dom/__init__.py
agent_lens_core/dom/buildDomTree.js
agent_lens_core/dom/service.py
agent_lens_core/dom/views.py
agent_lens_core/dom/history_tree_processor/service.py
agent_lens_core/dom/history_tree_processor/view.py
agent_lens_core/dom/tests/extraction_test.py
agent_lens_core/dom/tests/process_dom_test.py
agent_lens_core/telemetry/service.py
agent_lens_core/telemetry/views.py
agent_lens_core-0.1.1.dist-info/METADATA
agent_lens_core-0.1.1.dist-info/WHEEL
agent_lens_core-0.1.1.dist-info/licenses/LICENSE
agent_lens_core-0.1.1.dist-info/RECORD
